{
    "build": {
        "arduino": {
            "ldscript": "esp32_out.ld"
        },
        "core": "industrialshields",
        "extra_flags": " -DESP32PLC -DESP32PLC_38R",
        "f_cpu": "240000000L",
        "f_flash": "40000000L",
        "flash_mode": "dio",
        "mcu": "esp32",
        "variant": "esp32plc"
    },
    "connectivity": [
        "wifi",
        "bluetooth",
        "ethernet"
    ],
    "frameworks": [
        "arduino"
    ],
    "name": "ESP32 PLC 38R IO+",
    "upload": {
        "flash_size": "4MB",
        "maximum_ram_size": 327680,
        "maximum_size": 1310720,
        "require_upload_port": true,
        "speed": 460800
    },
    "url": "www.industrialshields.com/shop/esp32-plc-38r-2906",
    "vendor": "Industrial Shields"
}